include/ggml-alloc.h
include/ggml-backend.h
include/ggml-blas.h
include/ggml-cann.h
include/ggml-cpp.h
include/ggml-cpu.h
include/ggml-cuda.h
include/ggml-kompute.h
include/ggml-metal.h
include/ggml-opt.h
include/ggml-rpc.h
include/ggml-sycl.h
include/ggml-vulkan.h
include/ggml.h
include/gguf.h
include/whisper.h
lib/cmake/ggml/ggml-config.cmake
lib/cmake/ggml/ggml-version.cmake
lib/cmake/whisper/whisper-config.cmake
lib/cmake/whisper/whisper-version.cmake
lib/libggml-base.dylib
lib/libggml-blas.dylib
lib/libggml-cpu.dylib
lib/libggml-metal.dylib
lib/libggml.dylib
lib/libwhisper.1.7.6.dylib
lib/libwhisper.1.dylib
lib/libwhisper.dylib
lib/pkgconfig/whisper.pc
whisper_parallel_cpu/__init__.py
whisper_parallel_cpu/bindings.cpp
whisper_parallel_cpu/cli.py
whisper_parallel_cpu/model_manager.py
whisper_parallel_cpu/transcriber.cpp
whisper_parallel_cpu/whisper_parallel_cpu.cpython-313-darwin.so
whisper_parallel_cpu-1.0.1.dist-info/METADATA
whisper_parallel_cpu-1.0.1.dist-info/WHEEL
whisper_parallel_cpu-1.0.1.dist-info/entry_points.txt
whisper_parallel_cpu-1.0.1.dist-info/RECORD
