Metadata-Version: 2.4
Name: whisper-parallel-cpu
Version: 1.0.1
Summary: High-performance video transcription using whisper.cpp with automatic model downloading and CPU parallelism
Keywords: whisper,transcription,audio,speech,ai,ml,cpp,pybind11,cpu,parallel,multithreading
Author-Email: Krzysztof Furman <k_furman@outlook.com>
Maintainer-Email: Krzysztof Furman <k_furman@outlook.com>
License-Expression: MIT
Classifier: Development Status :: 5 - Production/Stable
Classifier: Intended Audience :: Developers
Classifier: Intended Audience :: Science/Research
Classifier: Operating System :: OS Independent
Classifier: Programming Language :: Python :: 3
Classifier: Programming Language :: Python :: 3.8
Classifier: Programming Language :: Python :: 3.9
Classifier: Programming Language :: Python :: 3.10
Classifier: Programming Language :: Python :: 3.11
Classifier: Programming Language :: Python :: 3.12
Classifier: Programming Language :: Python :: 3.13
Classifier: Topic :: Multimedia :: Sound/Audio :: Speech
Classifier: Topic :: Scientific/Engineering :: Artificial Intelligence
Classifier: Topic :: Software Development :: Libraries :: Python Modules
Classifier: Topic :: Multimedia :: Video
Project-URL: Homepage, https://github.com/krisfur/whisper-parallel-cpu
Project-URL: Repository, https://github.com/krisfur/whisper-parallel-cpu
Project-URL: Issues, https://github.com/krisfur/whisper-parallel-cpu/issues
Project-URL: Documentation, https://github.com/krisfur/whisper-parallel-cpu#readme
Requires-Python: >=3.8
Requires-Dist: psutil>=5.8.0
Provides-Extra: dev
Requires-Dist: pybind11>=2.11.0; extra == "dev"
Requires-Dist: build>=0.10.0; extra == "dev"
Requires-Dist: twine>=4.0.0; extra == "dev"
